fileencrypt/__init__.py
fileencrypt/cli.py
fileencrypt/decrypt.py
fileencrypt/encrypt.py
fileencrypt-0.1.2.dist-info/METADATA
fileencrypt-0.1.2.dist-info/WHEEL
fileencrypt-0.1.2.dist-info/entry_points.txt
fileencrypt-0.1.2.dist-info/top_level.txt
fileencrypt-0.1.2.dist-info/RECORD
