Metadata-Version: 2.4
Name: FileEncrypt
Version: 0.1.2
Summary: File compression, encryption and decryption using XChaCha20 cipher and Argon2id (CLI and Python module)
Home-page: https://github.com/jordanbmrd/file-encrypt
Author: dorit
Project-URL: Source, https://github.com/jordanbmrd/file-encrypt
Project-URL: Tracker, https://github.com/jordanbmrd/file-encrypt/issues
Classifier: Programming Language :: Python :: 3
Classifier: License :: OSI Approved :: MIT License
Classifier: Operating System :: OS Independent
Requires-Python: >=3.7
Requires-Dist: argon2-cffi
Requires-Dist: pynacl
Dynamic: author
Dynamic: classifier
Dynamic: description
Dynamic: description-content-type
Dynamic: home-page
Dynamic: project-url
Dynamic: requires-dist
Dynamic: requires-python
Dynamic: summary
